FRUFS.py
FRUFS-1.0.3.dist-info/METADATA
FRUFS-1.0.3.dist-info/WHEEL
FRUFS-1.0.3.dist-info/top_level.txt
FRUFS-1.0.3.dist-info/RECORD
