Metadata-Version: 2.1
Name: FRUFS
Version: 1.0.3
Summary: FRUFS stands for Feature Relevance based Unsupervised Feature Selection and is an unsupervised feature selection technique using supervised algorithms such as XGBoost
Home-page: https://github.com/atif-hassan/FRUFS
Author: Atif Hassan
Author-email: atif.hit.hassan@gmail.com
Classifier: Programming Language :: Python :: 3
Classifier: Programming Language :: Python :: 3.6
Classifier: Programming Language :: Python :: 3.7
Classifier: Operating System :: OS Independent
Requires-Dist: pandas
Requires-Dist: scikit-learn
Requires-Dist: numpy
Requires-Dist: joblib
Requires-Dist: matplotlib
Requires-Dist: seaborn
Requires-Dist: tqdm
